LICENSE
setup.py
./zero/__init__.py
./zero/client.py
./zero/codegen.py
./zero/common.py
./zero/errors.py
./zero/generate_client.py
./zero/logger.py
./zero/publisher.py
./zero/server.py
./zero/subscriber.py
./zero/type_util.py
./zero/zero_mq.py
hamuna_zero.egg-info/PKG-INFO
hamuna_zero.egg-info/SOURCES.txt
hamuna_zero.egg-info/dependency_links.txt
hamuna_zero.egg-info/requires.txt
hamuna_zero.egg-info/top_level.txt