Metadata-Version: 2.1
Name: hamuna-zero
Version: 1.0.1
Summary: Hamuna zero rpc framework based on pyzmq
Home-page: https://www.hamuna.club
Author: O.Push
Author-email: opush.developer@outlook.com
License: MIT
Platform: UNKNOWN
License-File: LICENSE
